FieldTracing/_WithinBounds.py
FieldTracing/__init__.py
FieldTracing/Euler/EulerStep.py
FieldTracing/Euler/EulerTrace.py
FieldTracing/Euler/__init__.py
FieldTracing/RK4/RK4Step.py
FieldTracing/RK4/RK4Trace.py
FieldTracing/RK4/__init__.py
FieldTracing-0.0.3.dist-info/LICENSE
FieldTracing-0.0.3.dist-info/METADATA
FieldTracing-0.0.3.dist-info/WHEEL
FieldTracing-0.0.3.dist-info/top_level.txt
FieldTracing-0.0.3.dist-info/RECORD
