Metadata-Version: 2.1
Name: FieldTracing
Version: 0.0.3
Summary: A package containing simple algorithms for field tracing.
Home-page: https://github.com/mattkjames7/FieldTracing
Author: Matthew Knight James
Author-email: mattkjames7@gmail.com
License: UNKNOWN
Platform: UNKNOWN
Classifier: Programming Language :: Python :: 3
Classifier: License :: OSI Approved :: MIT License
Classifier: Operating System :: OS Independent
Requires-Dist: numpy
